iosanita.contenttypes-1.0.8-py3.11-nspkg.pth
iosanita/contenttypes/__init__.py
iosanita/contenttypes/configure.zcml
iosanita/contenttypes/permissions.zcml
iosanita/contenttypes/setuphandlers.py
iosanita/contenttypes/testing.py
iosanita/contenttypes/utils.py
iosanita/contenttypes/adapters/__init__.py
iosanita/contenttypes/adapters/configure.zcml
iosanita/contenttypes/adapters/query.py
iosanita/contenttypes/adapters/schema_tweaks.py
iosanita/contenttypes/behaviors/__init__.py
iosanita/contenttypes/behaviors/a_chi_si_rivolge.py
iosanita/contenttypes/behaviors/argomenti.py
iosanita/contenttypes/behaviors/bando.py
iosanita/contenttypes/behaviors/configure.zcml
iosanita/contenttypes/behaviors/contatti.py
iosanita/contenttypes/behaviors/dove.py
iosanita/contenttypes/behaviors/evento.py
iosanita/contenttypes/behaviors/exclude_from_search.py
iosanita/contenttypes/behaviors/info_testata.py
iosanita/contenttypes/behaviors/metadata.py
iosanita/contenttypes/behaviors/multi_file.py
iosanita/contenttypes/behaviors/news.py
iosanita/contenttypes/behaviors/show_modified.py
iosanita/contenttypes/behaviors/sottotitolo.py
iosanita/contenttypes/behaviors/ulteriori_informazioni.py
iosanita/contenttypes/browser/__init__.py
iosanita/contenttypes/browser/configure.zcml
iosanita/contenttypes/browser/controlpanel.py
iosanita/contenttypes/browser/export_view.py
iosanita/contenttypes/browser/searchblock.py
iosanita/contenttypes/browser/static/.gitkeep
iosanita/contenttypes/browser/static/export_pdf.css
iosanita/contenttypes/browser/templates/export_pdf.pt
iosanita/contenttypes/content/__init__.py
iosanita/contenttypes/content/cartella_modulistica.py
iosanita/contenttypes/content/come_fare_per.py
iosanita/contenttypes/content/documento.py
iosanita/contenttypes/content/evento.py
iosanita/contenttypes/content/modulo.py
iosanita/contenttypes/content/persona.py
iosanita/contenttypes/content/punto_di_contatto.py
iosanita/contenttypes/content/servizio.py
iosanita/contenttypes/content/step.py
iosanita_contenttypes-1.0.8.dist-info/licenses/LICENSE
iosanita_contenttypes-1.0.8.dist-info/licenses/LICENSE.GPL
iosanita_contenttypes-1.0.8.dist-info/licenses/LICENSE.rst
iosanita_contenttypes-1.0.8.dist-info/METADATA
iosanita_contenttypes-1.0.8.dist-info/WHEEL
iosanita_contenttypes-1.0.8.dist-info/entry_points.txt
iosanita_contenttypes-1.0.8.dist-info/namespace_packages.txt
iosanita_contenttypes-1.0.8.dist-info/top_level.txt
iosanita_contenttypes-1.0.8.dist-info/RECORD
