Metadata-Version: 2.4
Name: iosanita.contenttypes
Version: 1.0.8
Summary: An add-on for Plone
Home-page: https://github.com/collective/iosanita.contenttypes
Author: RedTurtle Technology
Author-email: sviluppo@redturtle.it
License: GPL version 2
Project-URL: PyPI, https://pypi.org/project/iosanita.contenttypes/
Project-URL: Source, https://github.com/collective/iosanita.contenttypes
Project-URL: Tracker, https://github.com/collective/iosanita.contenttypes/issues
Keywords: Python Plone CMS
Classifier: Development Status :: 5 - Production/Stable
Classifier: Environment :: Web Environment
Classifier: Framework :: Plone
Classifier: Framework :: Plone :: Addon
Classifier: Framework :: Plone :: 6.0
Classifier: Programming Language :: Python
Classifier: Programming Language :: Python :: 3.8
Classifier: Programming Language :: Python :: 3.9
Classifier: Programming Language :: Python :: 3.10
Classifier: Programming Language :: Python :: 3.11
Classifier: Operating System :: OS Independent
Classifier: License :: OSI Approved :: GNU General Public License v2 (GPLv2)
Requires-Python: >=3.7
License-File: LICENSE
License-File: LICENSE.GPL
License-File: LICENSE.rst
Requires-Dist: setuptools
Requires-Dist: plone.api>=1.8.4
Requires-Dist: plone.app.dexterity
Requires-Dist: collective.volto.blocksfield>=2.2.0
Requires-Dist: collective.z3cform.datagridfield
Requires-Dist: redturtle.volto
Requires-Dist: redturtle.bandi
Requires-Dist: plone.restapi
Requires-Dist: collective.taxonomy
Requires-Dist: collective.address
Requires-Dist: collective.geolocationbehavior
Requires-Dist: collective.volto.enhancedlinks
Requires-Dist: weasyprint
Provides-Extra: test
Requires-Dist: plone.app.testing; extra == "test"
Requires-Dist: collective.volto.blocksfield; extra == "test"
Requires-Dist: plone.testing>=5.0.0; extra == "test"
Requires-Dist: plone.app.contenttypes; extra == "test"
Requires-Dist: plone.app.robotframework[debug]; extra == "test"
Requires-Dist: collective.MockMailHost; extra == "test"
Dynamic: author
Dynamic: author-email
Dynamic: classifier
Dynamic: description
Dynamic: home-page
Dynamic: keywords
Dynamic: license
Dynamic: license-file
Dynamic: project-url
Dynamic: provides-extra
Dynamic: requires-dist
Dynamic: requires-python
Dynamic: summary
